spot_motion_monitor/__init__.py
spot_motion_monitor/spot_motion_monitor_rc.py
spot_motion_monitor/camera/__init__.py
spot_motion_monitor/camera/base_camera.py
spot_motion_monitor/camera/camera_status.py
spot_motion_monitor/camera/gaussian_camera.py
spot_motion_monitor/camera/vimba_camera.py
spot_motion_monitor/config/__init__.py
spot_motion_monitor/config/base_config.py
spot_motion_monitor/config/buffer_model_config.py
spot_motion_monitor/config/camera_config.py
spot_motion_monitor/config/centroid_plot_config.py
spot_motion_monitor/config/data_config.py
spot_motion_monitor/config/full_frame_model_config.py
spot_motion_monitor/config/gaussian_camera_config.py
spot_motion_monitor/config/general_config.py
spot_motion_monitor/config/psd_plot_config.py
spot_motion_monitor/config/roi_frame_model_config.py
spot_motion_monitor/config/vimba_camera_config.py
spot_motion_monitor/controller/__init__.py
spot_motion_monitor/controller/camera_controller.py
spot_motion_monitor/controller/data_controller.py
spot_motion_monitor/controller/plot_ccd_controller.py
spot_motion_monitor/controller/plot_centroid_controller.py
spot_motion_monitor/controller/plot_psd_controller.py
spot_motion_monitor/models/__init__.py
spot_motion_monitor/models/buffer_model.py
spot_motion_monitor/models/full_frame_model.py
spot_motion_monitor/models/roi_frame_model.py
spot_motion_monitor/utils/__init__.py
spot_motion_monitor/utils/config_helpers.py
spot_motion_monitor/utils/constants.py
spot_motion_monitor/utils/css.py
spot_motion_monitor/utils/exceptions.py
spot_motion_monitor/utils/fft_calculator.py
spot_motion_monitor/utils/frame_information.py
spot_motion_monitor/utils/functions.py
spot_motion_monitor/utils/fwhm_calculator.py
spot_motion_monitor/utils/information_updater.py
spot_motion_monitor/utils/parser.py
spot_motion_monitor/utils/psd_calculator.py
spot_motion_monitor/utils/time_handler.py
spot_motion_monitor/utils/yaml_input.py
spot_motion_monitor/views/__init__.py
spot_motion_monitor-2.0.4.dist-info/AUTHORS.rst
spot_motion_monitor-2.0.4.dist-info/LICENSE
spot_motion_monitor-2.0.4.dist-info/METADATA
spot_motion_monitor-2.0.4.dist-info/WHEEL
spot_motion_monitor-2.0.4.dist-info/entry_points.txt
spot_motion_monitor-2.0.4.dist-info/top_level.txt
spot_motion_monitor-2.0.4.dist-info/RECORD
