Metadata-Version: 2.1
Name: spot-motion-monitor
Version: 2.0.4
Summary: User interface for Spot Seeing Monitor.
Home-page: https://github.com/lsst-sitcom/spot_motion_monitor
Author: Michael Reuter
Author-email: mareuter@lsst.org
License: BSD 3-Clause License
Keywords: spot_motion_monitor
Platform: UNKNOWN
Classifier: Development Status :: 5 - Production/Stable
Classifier: Intended Audience :: Science/Research
Classifier: License :: OSI Approved :: BSD License
Classifier: Natural Language :: English
Classifier: Programming Language :: Python :: 3
Classifier: Programming Language :: Python :: 3.7
Classifier: Programming Language :: Python :: 3.8
Classifier: Programming Language :: Python :: 3.9
License-File: LICENSE
License-File: AUTHORS.rst
Requires-Dist: astropy
Requires-Dist: PyQt5
Requires-Dist: scipy
Requires-Dist: pandas
Requires-Dist: pyqtgraph
Requires-Dist: matplotlib
Requires-Dist: tables
Requires-Dist: pymba (==0.3.5)
Requires-Dist: pytz
Requires-Dist: PyYAML
